<?xml version="1.0" encoding="UTF-8" standalone="yes"?>
<Properties xmlns="http://schemas.openxmlformats.org/officeDocument/2006/extended-properties" xmlns:vt="http://schemas.openxmlformats.org/officeDocument/2006/docPropsVTypes"><Template></Template><TotalTime>54</TotalTime><Application>LibreOffice/5.1.2.2$MacOSX_X86_64 LibreOffice_project/d3bf12ecb743fc0d20e0be0c58ca359301eb705f</Application><Pages>1</Pages><Words>76</Words><Characters>489</Characters><CharactersWithSpaces>563</CharactersWithSpaces><Paragraphs>3</Paragraphs></Properties>